llama_index/embeddings/gaudi/__init__.py
llama_index/embeddings/gaudi/base.py
llama_index/embeddings/gaudi/utils.py
llama_index_embeddings_gaudi-0.3.1.dist-info/METADATA
llama_index_embeddings_gaudi-0.3.1.dist-info/WHEEL
llama_index_embeddings_gaudi-0.3.1.dist-info/licenses/LICENSE
llama_index_embeddings_gaudi-0.3.1.dist-info/RECORD
